discordmusiclib/__init__.py
discordmusiclib/main.py
discordmusiclib/simple_api.py
discordmusiclib/youtube_search.py
discordmusiclib-1.0.0.dist-info/LICENSE
discordmusiclib-1.0.0.dist-info/METADATA
discordmusiclib-1.0.0.dist-info/WHEEL
discordmusiclib-1.0.0.dist-info/top_level.txt
discordmusiclib-1.0.0.dist-info/RECORD
