Metadata-Version: 2.1
Name: discordmusiclib
Version: 1.0.0
Summary: A custom YouTube audio downloader for Discord bots
Home-page: https://github.com/yourusername/discordmusiclib
Author: Your Name
Author-email: your.email@example.com
Keywords: discord,music,youtube,audio,bot
Classifier: Development Status :: 4 - Beta
Classifier: Intended Audience :: Developers
Classifier: License :: OSI Approved :: MIT License
Classifier: Operating System :: OS Independent
Classifier: Programming Language :: Python :: 3
Classifier: Programming Language :: Python :: 3.8
Classifier: Programming Language :: Python :: 3.9
Classifier: Programming Language :: Python :: 3.10
Classifier: Programming Language :: Python :: 3.11
Classifier: Topic :: Software Development :: Libraries :: Python Modules
Classifier: Topic :: Multimedia :: Sound/Audio
Requires-Python: >=3.8
License-File: LICENSE
Requires-Dist: aiohttp >=3.8.0
Requires-Dist: discord.py >=2.0.0
Provides-Extra: dev
Requires-Dist: pytest ; extra == 'dev'
Requires-Dist: black ; extra == 'dev'
Requires-Dist: flake8 ; extra == 'dev'
